{
  "model_id": "patrickjohncyh/fashion-clip",
  "embedding_dim": 512,
  "image_weight": 0.6,
  "text_weight": 0.4,
  "n_products": 68,
  "id_to_index": {
    "myntra_28569210": 0,
    "ajio_469618352": 1,
    "ajio_443087217": 2,
    "ajio_464835118": 3,
    "ajio_703306501": 4,
    "ajio_466576129": 5,
    "ajio_703182002": 6,
    "ajio_467147176": 7,
    "ajio_703450523": 8,
    "ajio_469763526": 9,
    "ajio_703187803": 10,
    "ajio_703351510": 11,
    "ajio_700825576": 12,
    "myntra_38692620": 13,
    "myntra_36794231": 14,
    "myntra_42184814": 15,
    "myntra_29132512": 16,
    "myntra_23237806": 17,
    "nykaa_21046502": 18,
    "nykaa_24178529": 19,
    "nykaa_25523123": 20,
    "nykaa_21896203": 21,
    "nykaa_20942213": 22,
    "myntra_40399611": 23,
    "myntra_38200553": 24,
    "myntra_34682942": 25,
    "myntra_41163758": 26,
    "nykaa_19331662": 27,
    "nykaa_21742536": 28,
    "nykaa_19356700": 29,
    "nykaa_22006528": 30,
    "myntra_11990814": 31,
    "myntra_39522716": 32,
    "myntra_30308778": 33,
    "myntra_41733768": 34,
    "myntra_31751105": 35,
    "myntra_26814366": 36,
    "myntra_32069236": 37,
    "myntra_42540276": 38,
    "myntra_41756001": 39,
    "myntra_38487469": 40,
    "ajio_701467182": 41,
    "ajio_703543037": 42,
    "ajio_702390240": 43,
    "ajio_701677398": 44,
    "nykaa_13632320": 45,
    "ajio_702733799": 46,
    "ajio_702454568": 47,
    "ajio_702780607": 48,
    "myntra_36090580": 49,
    "myntra_24130018": 50,
    "myntra_15660676": 51,
    "myntra_39451752": 52,
    "myntra_41578752": 53,
    "myntra_625852": 54,
    "myntra_7451803": 55,
    "myntra_30441198": 56,
    "nykaa_24377703": 57,
    "nykaa_22909654": 58,
    "ajio_702013278": 59,
    "ajio_700917335": 60,
    "ajio_469683825": 61,
    "ajio_700692049": 62,
    "ajio_701984081": 63,
    "ajio_464207650": 64,
    "ajio_4935353720": 65,
    "ajio_4934125790": 66,
    "ajio_702546309": 67
  },
  "index_to_id": {
    "0": "myntra_28569210",
    "1": "ajio_469618352",
    "2": "ajio_443087217",
    "3": "ajio_464835118",
    "4": "ajio_703306501",
    "5": "ajio_466576129",
    "6": "ajio_703182002",
    "7": "ajio_467147176",
    "8": "ajio_703450523",
    "9": "ajio_469763526",
    "10": "ajio_703187803",
    "11": "ajio_703351510",
    "12": "ajio_700825576",
    "13": "myntra_38692620",
    "14": "myntra_36794231",
    "15": "myntra_42184814",
    "16": "myntra_29132512",
    "17": "myntra_23237806",
    "18": "nykaa_21046502",
    "19": "nykaa_24178529",
    "20": "nykaa_25523123",
    "21": "nykaa_21896203",
    "22": "nykaa_20942213",
    "23": "myntra_40399611",
    "24": "myntra_38200553",
    "25": "myntra_34682942",
    "26": "myntra_41163758",
    "27": "nykaa_19331662",
    "28": "nykaa_21742536",
    "29": "nykaa_19356700",
    "30": "nykaa_22006528",
    "31": "myntra_11990814",
    "32": "myntra_39522716",
    "33": "myntra_30308778",
    "34": "myntra_41733768",
    "35": "myntra_31751105",
    "36": "myntra_26814366",
    "37": "myntra_32069236",
    "38": "myntra_42540276",
    "39": "myntra_41756001",
    "40": "myntra_38487469",
    "41": "ajio_701467182",
    "42": "ajio_703543037",
    "43": "ajio_702390240",
    "44": "ajio_701677398",
    "45": "nykaa_13632320",
    "46": "ajio_702733799",
    "47": "ajio_702454568",
    "48": "ajio_702780607",
    "49": "myntra_36090580",
    "50": "myntra_24130018",
    "51": "myntra_15660676",
    "52": "myntra_39451752",
    "53": "myntra_41578752",
    "54": "myntra_625852",
    "55": "myntra_7451803",
    "56": "myntra_30441198",
    "57": "nykaa_24377703",
    "58": "nykaa_22909654",
    "59": "ajio_702013278",
    "60": "ajio_700917335",
    "61": "ajio_469683825",
    "62": "ajio_700692049",
    "63": "ajio_701984081",
    "64": "ajio_464207650",
    "65": "ajio_4935353720",
    "66": "ajio_4934125790",
    "67": "ajio_702546309"
  },
  "products": {
    "myntra_28569210": {
      "index": 0,
      "name": "Cotton Slim Fit Formal Shirt",
      "brand": "Arrow",
      "price_inr": 1099.0,
      "rating": 4.5,
      "gender": "men",
      "wear_type": "western",
      "category": "formal-shirts",
      "category_label": "formal shirts",
      "occasion": "office",
      "image_path": "D:\\DarexAi\\images\\myntra\\28569210.jpg",
      "embed_text": "Cotton Slim Fit Formal Shirt | Arrow | formal shirts | office | western | men western formal-shirts office Arrow | White solid opaque Formal shirt ,has a cutaway collar, button placket, 1 pocket, long",
      "has_image": true
    },
    "ajio_469618352": {
      "index": 1,
      "name": "Men Regular Fit 2-Piece Suit Set",
      "brand": "ARROW",
      "price_inr": 5000.0,
      "rating": 3.3,
      "gender": "men",
      "wear_type": "western",
      "category": "suits",
      "category_label": "suits",
      "occasion": "wedding",
      "image_path": "D:\\DarexAi\\images\\ajio\\469618352.jpg",
      "embed_text": "Men Regular Fit 2-Piece Suit Set | ARROW | suits | wedding | western | men western suits wedding ARROW | Grey suit for men from ARROW. It features a regular fit. Made for weddings and festive celebrat",
      "has_image": true
    },
    "ajio_443087217": {
      "index": 2,
      "name": "Men Oversized Fit Crew-Neck Sweatshirt",
      "brand": "DNMX",
      "price_inr": 300.0,
      "rating": 4.0,
      "gender": "men",
      "wear_type": "western",
      "category": "sweatshirts",
      "category_label": "sweatshirts",
      "occasion": "casual",
      "image_path": "D:\\DarexAi\\images\\ajio\\443087217.jpg",
      "embed_text": "Men Oversized Fit Crew-Neck Sweatshirt | DNMX | sweatshirts | casual | western | men western sweatshirts casual DNMX | Dark grey sweatshirt for men from DNMX. It features an oversized silhouette. Easy",
      "has_image": true
    },
    "ajio_464835118": {
      "index": 3,
      "name": "Track Pants with Elasticated Drawstrings",
      "brand": "Jack & Jones",
      "price_inr": 602.0,
      "rating": 3.8,
      "gender": "men",
      "wear_type": "western",
      "category": "track-pants",
      "category_label": "track pants",
      "occasion": "sports",
      "image_path": "D:\\DarexAi\\images\\ajio\\464835118.jpg",
      "embed_text": "Track Pants with Elasticated Drawstrings | Jack & Jones | track pants | sports | western | men western track-pants sports Jack & Jones | Brown pair of track pants for men from Jack & Jones. It feature",
      "has_image": true
    },
    "ajio_703306501": {
      "index": 4,
      "name": "Men Regular Fit Linen Shirt",
      "brand": "NEONOMAD",
      "price_inr": 960.0,
      "rating": 0.0,
      "gender": "men",
      "wear_type": "western",
      "category": "linen-shirts",
      "category_label": "linen shirts",
      "occasion": "vacation",
      "image_path": "D:\\DarexAi\\images\\ajio\\703306501.jpg",
      "embed_text": "Men Regular Fit Linen Shirt | NEONOMAD | linen shirts | vacation | western | men western linen-shirts vacation NEONOMAD | Sea green linen shirt for men from NEONOMAD. It features a regular fit and a l",
      "has_image": true
    },
    "ajio_466576129": {
      "index": 5,
      "name": "Men Texture Solid Indowestern Sherwani Churidar with Dupatta Set",
      "brand": "KISAH",
      "price_inr": 7799.0,
      "rating": 3.4,
      "gender": "men",
      "wear_type": "ethnic",
      "category": "sherwanis",
      "category_label": "sherwanis",
      "occasion": "wedding",
      "image_path": "D:\\DarexAi\\images\\ajio\\466576129.jpg",
      "embed_text": "Men Texture Solid Indowestern Sherwani Churidar with Dupatta Set | KISAH | sherwanis | wedding | ethnic | men ethnic sherwanis wedding KISAH | Beige sherwani for men from KISAH. It features a solid co",
      "has_image": true
    },
    "ajio_703182002": {
      "index": 6,
      "name": "Women Bodycon Midi Length Dress",
      "brand": "Fyre Rose",
      "price_inr": 765.0,
      "rating": 0.0,
      "gender": "women",
      "wear_type": "western",
      "category": "party-dresses",
      "category_label": "party dresses",
      "occasion": "party",
      "image_path": "D:\\DarexAi\\images\\ajio\\703182002.jpg",
      "embed_text": "Women Bodycon Midi Length Dress | Fyre Rose | party dresses | party | western | women western party-dresses party Fyre Rose | Black party dress for women from Fyre Rose. It features a body-hugging fit",
      "has_image": true
    },
    "ajio_467147176": {
      "index": 7,
      "name": "Women Floral Woven Banarasi Silk Saree",
      "brand": "Styleelite",
      "price_inr": 615.0,
      "rating": 2.9,
      "gender": "women",
      "wear_type": "ethnic",
      "category": "wedding-sarees",
      "category_label": "wedding sarees",
      "occasion": "wedding",
      "image_path": "D:\\DarexAi\\images\\ajio\\467147176.jpg",
      "embed_text": "Women Floral Woven Banarasi Silk Saree | Styleelite | wedding sarees | wedding | ethnic | women ethnic wedding-sarees wedding Styleelite | Red wedding saree for women from Styleelite. It features a fl",
      "has_image": true
    },
    "ajio_703450523": {
      "index": 8,
      "name": "Women Elegance Sharara Kurta Set",
      "brand": "Nyrika",
      "price_inr": 1300.0,
      "rating": 0.0,
      "gender": "women",
      "wear_type": "ethnic",
      "category": "sharara-sets",
      "category_label": "sharara sets",
      "occasion": "festive",
      "image_path": "D:\\DarexAi\\images\\ajio\\703450523.jpg",
      "embed_text": "Women Elegance Sharara Kurta Set | Nyrika | sharara sets | festive | ethnic | women ethnic sharara-sets festive Nyrika | Purple sharara set for women from Nyrika. Suited to festive and celebratory occ",
      "has_image": true
    },
    "ajio_469763526": {
      "index": 9,
      "name": "Men Softride Carson Fresh Running Shoes",
      "brand": "Puma",
      "price_inr": 2535.0,
      "rating": 2.5,
      "gender": "men",
      "wear_type": "footwear",
      "category": "running-shoes",
      "category_label": "running shoes",
      "occasion": "sports",
      "image_path": "D:\\DarexAi\\images\\ajio\\469763526.jpg",
      "embed_text": "Men Softride Carson Fresh Running Shoes | Puma | running shoes | sports | footwear | men footwear running-shoes sports Puma | Green pair of running shoes for men from Puma. Built for workouts and acti",
      "has_image": true
    },
    "ajio_703187803": {
      "index": 10,
      "name": "Women Lace-Up Fastening Sneakers",
      "brand": "Forever Glam by Pantaloons",
      "price_inr": 1049.0,
      "rating": 5.0,
      "gender": "women",
      "wear_type": "footwear",
      "category": "sneakers",
      "category_label": "sneakers",
      "occasion": "casual",
      "image_path": "D:\\DarexAi\\images\\ajio\\703187803.jpg",
      "embed_text": "Women Lace-Up Fastening Sneakers | Forever Glam by Pantaloons | sneakers | casual | footwear | women footwear sneakers casual Forever Glam by Pantaloons | Cream pair of sneakers for women from Forever",
      "has_image": true
    },
    "ajio_703351510": {
      "index": 11,
      "name": "Women Fusion Embellished Juttis",
      "brand": "DFR",
      "price_inr": 2699.0,
      "rating": 0.0,
      "gender": "women",
      "wear_type": "footwear",
      "category": "ethnic-footwear",
      "category_label": "ethnic footwear",
      "occasion": "festive",
      "image_path": "D:\\DarexAi\\images\\ajio\\703351510.jpg",
      "embed_text": "Women Fusion Embellished Juttis | DFR | ethnic footwear | festive | footwear | women footwear ethnic-footwear festive DFR | Cream pair of ethnic footwear for women from DFR. It features embellishments",
      "has_image": true
    },
    "ajio_700825576": {
      "index": 12,
      "name": "Women Stone-Studded Necklace & Earrings Set",
      "brand": "VATSALYA",
      "price_inr": 305.0,
      "rating": 3.3,
      "gender": "women",
      "wear_type": "accessory",
      "category": "necklaces",
      "category_label": "necklaces",
      "occasion": "wedding",
      "image_path": "D:\\DarexAi\\images\\ajio\\700825576.jpg",
      "embed_text": "Women Stone-Studded Necklace & Earrings Set | VATSALYA | necklaces | wedding | accessory | women accessory necklaces wedding VATSALYA | Pink necklace for women from VATSALYA. Made for weddings and fes",
      "has_image": true
    },
    "myntra_38692620": {
      "index": 13,
      "name": "Slim Fit Casual Shirt",
      "brand": "Aldeno",
      "price_inr": 759.0,
      "rating": 4.5,
      "gender": "men",
      "wear_type": "western",
      "category": "casual-shirts",
      "category_label": "casual shirts",
      "occasion": "casual",
      "image_path": "D:\\DarexAi\\images\\myntra\\38692620.jpg",
      "embed_text": "Slim Fit Casual Shirt | Aldeno | casual shirts | casual | western | men western casual-shirts casual Aldeno | Navy blue solid opaque Casual shirt ,has a cutaway collar, button placket, na pocket, long",
      "has_image": true
    },
    "myntra_36794231": {
      "index": 14,
      "name": "Textured Spread Collar Shirt",
      "brand": "Instafab Plus",
      "price_inr": 1065.0,
      "rating": 4.5,
      "gender": "men",
      "wear_type": "western",
      "category": "party-shirts",
      "category_label": "party shirts",
      "occasion": "party",
      "image_path": "D:\\DarexAi\\images\\myntra\\36794231.jpg",
      "embed_text": "Textured Spread Collar Shirt | Instafab Plus | party shirts | party | western | men western party-shirts party Instafab Plus | Black and white textured opaque party shirt ,has a spread collar, button ",
      "has_image": true
    },
    "myntra_42184814": {
      "index": 15,
      "name": "Unisex Cotton T-shirt",
      "brand": "Rigo",
      "price_inr": 599.0,
      "rating": 0.0,
      "gender": "men",
      "wear_type": "western",
      "category": "tshirts",
      "category_label": "tshirts",
      "occasion": "casual",
      "image_path": "D:\\DarexAi\\images\\myntra\\42184814.jpg",
      "embed_text": "Unisex Cotton T-shirt | Rigo | tshirts | casual | western | men western tshirts casual Rigo | Navy Blue Tshirt for Unisex | Solid | Regular length | Round Neck | Three-quarter, Regular Sleeves | Knitt",
      "has_image": true
    },
    "myntra_29132512": {
      "index": 16,
      "name": "Polo Collar Cotton T-shirt",
      "brand": "XYXX",
      "price_inr": 599.0,
      "rating": 4.1,
      "gender": "men",
      "wear_type": "western",
      "category": "polo-tshirts",
      "category_label": "polo tshirts",
      "occasion": "casual",
      "image_path": "D:\\DarexAi\\images\\myntra\\29132512.jpg",
      "embed_text": "Polo Collar Cotton T-shirt | XYXX | polo tshirts | casual | western | men western polo-tshirts casual XYXX | With Nova, the traditional Polo makes a stylish comeback. We took the breathable and utterl",
      "has_image": true
    },
    "myntra_23237806": {
      "index": 17,
      "name": "Men Slim Fit Trousers",
      "brand": "Raymond",
      "price_inr": 1224.0,
      "rating": 4.3,
      "gender": "men",
      "wear_type": "western",
      "category": "trousers",
      "category_label": "trousers",
      "occasion": "office",
      "image_path": "D:\\DarexAi\\images\\myntra\\23237806.jpg",
      "embed_text": "Men Slim Fit Trousers | Raymond | trousers | office | western | men western trousers office Raymond | Grey woven formal trousers | Slim fit | Mid-rise | Length: regular | Pattern: textured self design",
      "has_image": true
    },
    "nykaa_21046502": {
      "index": 18,
      "name": "Blue Slim Fit Mid Rise Jeans",
      "brand": "AD By Arvind",
      "price_inr": 1350.0,
      "rating": 0.0,
      "gender": "men",
      "wear_type": "western",
      "category": "jeans",
      "category_label": "jeans",
      "occasion": "casual",
      "image_path": "D:\\DarexAi\\images\\nykaa\\21046502.jpg",
      "embed_text": "Blue Slim Fit Mid Rise Jeans | AD By Arvind | jeans | casual | western | men western jeans casual AD By Arvind | Buy AD By Arvind Blue Slim Fit Mid Rise Jeans (38) online at best prices on Nykaa Fashi",
      "has_image": true
    },
    "nykaa_24178529": {
      "index": 19,
      "name": "Tea Green Men Chinos",
      "brand": "The Souled Store",
      "price_inr": 1500.0,
      "rating": 0.0,
      "gender": "men",
      "wear_type": "western",
      "category": "chinos",
      "category_label": "chinos",
      "occasion": "casual",
      "image_path": "D:\\DarexAi\\images\\nykaa\\24178529.jpg",
      "embed_text": "Tea Green Men Chinos | The Souled Store | chinos | casual | western | men western chinos casual The Souled Store | Buy The Souled Store Tea Green Men Chinos (28) online at best prices on Nykaa Fashion",
      "has_image": true
    },
    "nykaa_25523123": {
      "index": 20,
      "name": "Mens Navy Blue Pure Cotton Ultra Light Lounge Shorts",
      "brand": "DaMENSCH",
      "price_inr": 756.0,
      "rating": 0.0,
      "gender": "men",
      "wear_type": "western",
      "category": "shorts",
      "category_label": "shorts",
      "occasion": "casual",
      "image_path": "D:\\DarexAi\\images\\nykaa\\25523123.jpg",
      "embed_text": "Mens Navy Blue Pure Cotton Ultra Light Lounge Shorts | DaMENSCH | shorts | casual | western | men western shorts casual DaMENSCH | Buy DaMENSCH Mens Navy Blue Pure Cotton Ultra Light Lounge Shorts (S)",
      "has_image": true
    },
    "nykaa_21896203": {
      "index": 21,
      "name": "Women Navy Blue Print Long Sleeves Formal Shirt",
      "brand": "Van Heusen",
      "price_inr": 1225.0,
      "rating": 0.0,
      "gender": "women",
      "wear_type": "western",
      "category": "formal-shirts",
      "category_label": "formal shirts",
      "occasion": "office",
      "image_path": "D:\\DarexAi\\images\\nykaa\\21896203.jpg",
      "embed_text": "Women Navy Blue Print Long Sleeves Formal Shirt | Van Heusen | formal shirts | office | western | women western formal-shirts office Van Heusen | Buy Van Heusen Women Navy Blue Print Long Sleeves Form",
      "has_image": true
    },
    "nykaa_20942213": {
      "index": 22,
      "name": "Marquee White Sequin Printed Dress",
      "brand": "VERO MODA",
      "price_inr": 4550.0,
      "rating": 0.0,
      "gender": "women",
      "wear_type": "western",
      "category": "casual-dresses",
      "category_label": "casual dresses",
      "occasion": "casual",
      "image_path": "D:\\DarexAi\\images\\nykaa\\20942213.jpg",
      "embed_text": "Marquee White Sequin Printed Dress | VERO MODA | casual dresses | casual | western | women western casual-dresses casual VERO MODA | Buy VERO MODA Marquee White Sequin Printed Dress (XS) online at bes",
      "has_image": true
    },
    "myntra_40399611": {
      "index": 23,
      "name": "Roman Silk Embroidery Kurta",
      "brand": "House of Pataudi",
      "price_inr": 1329.0,
      "rating": 0.0,
      "gender": "men",
      "wear_type": "ethnic",
      "category": "kurta-sets",
      "category_label": "kurta sets",
      "occasion": "festive",
      "image_path": "D:\\DarexAi\\images\\myntra\\40399611.jpg",
      "embed_text": "Roman Silk Embroidery Kurta | House of Pataudi | kurta sets | festive | ethnic | men ethnic kurta-sets festive House of Pataudi | This kurta set consists of Kurta and pyjamas with Dupatta | kurta Desi",
      "has_image": true
    },
    "myntra_38200553": {
      "index": 24,
      "name": "Cotton Woven Nehru Jacket",
      "brand": "Fabindia",
      "price_inr": 1199.0,
      "rating": 4.4,
      "gender": "men",
      "wear_type": "ethnic",
      "category": "nehru-jackets",
      "category_label": "nehru jackets",
      "occasion": "festive",
      "image_path": "D:\\DarexAi\\images\\myntra\\38200553.jpg",
      "embed_text": "Cotton Woven Nehru Jacket | Fabindia | nehru jackets | festive | ethnic | men ethnic nehru-jackets festive Fabindia | Navy blue solid woven Nehru jacket, has a mandarin collar, a full button placket, ",
      "has_image": true
    },
    "myntra_34682942": {
      "index": 25,
      "name": "Ruched Asymmetrical Midi Dress",
      "brand": "MANGO",
      "price_inr": 2397.0,
      "rating": 4.4,
      "gender": "women",
      "wear_type": "western",
      "category": "party-dresses",
      "category_label": "party dresses",
      "occasion": "party",
      "image_path": "D:\\DarexAi\\images\\myntra\\34682942.jpg",
      "embed_text": "Ruched Asymmetrical Midi Dress | MANGO | party dresses | party | western | women western party-dresses party MANGO | Burgundy solid dress | One shoulder | Sleeveless | Gathered and pleated detail | Ru",
      "has_image": true
    },
    "myntra_41163758": {
      "index": 26,
      "name": "Women Straight Fit High-Rise Jeans",
      "brand": "U.S. Polo Assn. Women",
      "price_inr": 1826.0,
      "rating": 4.1,
      "gender": "women",
      "wear_type": "western",
      "category": "jeans",
      "category_label": "jeans",
      "occasion": "casual",
      "image_path": "D:\\DarexAi\\images\\myntra\\41163758.jpg",
      "embed_text": "Women Straight Fit High-Rise Jeans | U.S. Polo Assn. Women | jeans | casual | western | women western jeans casual U.S. Polo Assn. Women | Medium shade, Light Fade Blue jeans | Straight Fit, High-Rise",
      "has_image": true
    },
    "nykaa_19331662": {
      "index": 27,
      "name": "Women Olive Green High Rise Formal Trousers",
      "brand": "Powersutra",
      "price_inr": 1920.0,
      "rating": 0.0,
      "gender": "women",
      "wear_type": "western",
      "category": "trousers",
      "category_label": "trousers",
      "occasion": "office",
      "image_path": "D:\\DarexAi\\images\\nykaa\\19331662.jpg",
      "embed_text": "Women Olive Green High Rise Formal Trousers | Powersutra | trousers | office | western | women western trousers office Powersutra | Buy Powersutra Women Olive Green High Rise Formal Trousers online at",
      "has_image": true
    },
    "nykaa_21742536": {
      "index": 28,
      "name": "Women Solid Bright Blue Bonnet Midi Skirt",
      "brand": "KOTTY",
      "price_inr": 800.0,
      "rating": 0.0,
      "gender": "women",
      "wear_type": "western",
      "category": "skirts",
      "category_label": "skirts",
      "occasion": "casual",
      "image_path": "D:\\DarexAi\\images\\nykaa\\21742536.jpg",
      "embed_text": "Women Solid Bright Blue Bonnet Midi Skirt | KOTTY | skirts | casual | western | women western skirts casual KOTTY | Buy KOTTY Women Solid Bright Blue Bonnet Midi Skirt (L) online at best prices on Nyk",
      "has_image": true
    },
    "nykaa_19356700": {
      "index": 29,
      "name": "Zen Round Neck Tank Top for Women, 4 Way Stretchable",
      "brand": "Hunnit",
      "price_inr": 1155.0,
      "rating": 5.0,
      "gender": "women",
      "wear_type": "western",
      "category": "activewear",
      "category_label": "activewear",
      "occasion": "sports",
      "image_path": "D:\\DarexAi\\images\\nykaa\\19356700.jpg",
      "embed_text": "Zen Round Neck Tank Top for Women, 4 Way Stretchable | Hunnit | activewear | sports | western | women western activewear sports Hunnit | Buy Hunnit Zen Round Neck Tank Top for Women, 4 Way Stretchable",
      "has_image": true
    },
    "nykaa_22006528": {
      "index": 30,
      "name": "Signature Denim Jacket",
      "brand": "Bonkers Corner",
      "price_inr": 2253.0,
      "rating": 0.0,
      "gender": "men",
      "wear_type": "western",
      "category": "denim-jackets",
      "category_label": "denim jackets",
      "occasion": "casual",
      "image_path": "D:\\DarexAi\\images\\nykaa\\22006528.jpg",
      "embed_text": "Signature Denim Jacket | Bonkers Corner | denim jackets | casual | western | men western denim-jackets casual Bonkers Corner | Buy Bonkers Corner Signature Denim Jacket (XS) online at best prices on N",
      "has_image": true
    },
    "myntra_11990814": {
      "index": 31,
      "name": "Open Knit Pullover Sweater",
      "brand": "Roadster",
      "price_inr": 742.0,
      "rating": 4.4,
      "gender": "women",
      "wear_type": "western",
      "category": "sweaters",
      "category_label": "sweaters",
      "occasion": "winter",
      "image_path": "D:\\DarexAi\\images\\myntra\\11990814.jpg",
      "embed_text": "Open Knit Pullover Sweater | Roadster | sweaters | winter | western | women western sweaters winter Roadster | Rust red open knit pullover sweater, has a mock collar, long sleeves, half zipper closure",
      "has_image": true
    },
    "myntra_39522716": {
      "index": 32,
      "name": "Floral Print Peplum Top",
      "brand": "Anouk Mirage",
      "price_inr": 402.0,
      "rating": 3.8,
      "gender": "women",
      "wear_type": "western",
      "category": "tops",
      "category_label": "tops",
      "occasion": "casual",
      "image_path": "D:\\DarexAi\\images\\myntra\\39522716.jpg",
      "embed_text": "Floral Print Peplum Top | Anouk Mirage | tops | casual | western | women western tops casual Anouk Mirage | Off White Regular Peplum tops | Floral Print | Square Neck, three-quarter, Regular Sleeves s",
      "has_image": true
    },
    "myntra_30308778": {
      "index": 33,
      "name": "Formal Shirt",
      "brand": "Chemistry",
      "price_inr": 703.0,
      "rating": 4.3,
      "gender": "women",
      "wear_type": "western",
      "category": "formal-shirts",
      "category_label": "formal shirts",
      "occasion": "office",
      "image_path": "D:\\DarexAi\\images\\myntra\\30308778.jpg",
      "embed_text": "Formal Shirt | Chemistry | formal shirts | office | western | women western formal-shirts office Chemistry | Maroon solid opaque Formal shirt ,has a spread collar, button placket, 2 patch pocket, long",
      "has_image": true
    },
    "myntra_41733768": {
      "index": 34,
      "name": "Bodycon Midi Dress",
      "brand": "MULVARI",
      "price_inr": 590.0,
      "rating": 4.4,
      "gender": "women",
      "wear_type": "western",
      "category": "party-dresses",
      "category_label": "party dresses",
      "occasion": "party",
      "image_path": "D:\\DarexAi\\images\\myntra\\41733768.jpg",
      "embed_text": "Bodycon Midi Dress | MULVARI | party dresses | party | western | women western party-dresses party MULVARI | Maroon and Maroon Solid Bodycon dresses | Square Neck | Sleeveless, No Sleeves | Midi lengt",
      "has_image": true
    },
    "myntra_31751105": {
      "index": 35,
      "name": "Open Toe Kitten Heel Sandals",
      "brand": "Mochi",
      "price_inr": 824.0,
      "rating": 4.4,
      "gender": "women",
      "wear_type": "footwear",
      "category": "heels",
      "category_label": "heels",
      "occasion": "party",
      "image_path": "D:\\DarexAi\\images\\myntra\\31751105.jpg",
      "embed_text": "Open Toe Kitten Heel Sandals | Mochi | heels | party | footwear | women footwear heels party Mochi | A pair of brown sandals ,has regular ankle and lace-ups | Synthetic colourblocked upper with wester",
      "has_image": true
    },
    "myntra_26814366": {
      "index": 36,
      "name": "Bow Detail Kitten Heel Pumps",
      "brand": "Carlton London",
      "price_inr": 1249.0,
      "rating": 4.1,
      "gender": "women",
      "wear_type": "footwear",
      "category": "heels",
      "category_label": "heels",
      "occasion": "party",
      "image_path": "D:\\DarexAi\\images\\myntra\\26814366.jpg",
      "embed_text": "Bow Detail Kitten Heel Pumps | Carlton London | heels | party | footwear | women footwear heels party Carlton London | A pair of white textured bow detail kitten heel pumps,has regular ankle and close",
      "has_image": true
    },
    "myntra_32069236": {
      "index": 37,
      "name": "Women Stiletto Pumps",
      "brand": "Shoetopia",
      "price_inr": 624.0,
      "rating": 4.5,
      "gender": "women",
      "wear_type": "footwear",
      "category": "heels",
      "category_label": "heels",
      "occasion": "party",
      "image_path": "D:\\DarexAi\\images\\myntra\\32069236.jpg",
      "embed_text": "Women Stiletto Pumps | Shoetopia | heels | party | footwear | women footwear heels party Shoetopia | A pair of white pumps ,has regular ankle and closed back | Synthetic solid upper with western - emb",
      "has_image": true
    },
    "myntra_42540276": {
      "index": 38,
      "name": "Classic Women's Heels",
      "brand": "Lavie",
      "price_inr": 899.0,
      "rating": 0.0,
      "gender": "women",
      "wear_type": "footwear",
      "category": "heels",
      "category_label": "heels",
      "occasion": "party",
      "image_path": "D:\\DarexAi\\images\\myntra\\42540276.jpg",
      "embed_text": "Classic Women's Heels | Lavie | heels | party | footwear | women footwear heels party Lavie | A pair of Gold-Toned and Gold-Toned Pumps ,has Regular ankle and Backstrap | Synthetic Solid upper with We",
      "has_image": true
    },
    "myntra_41756001": {
      "index": 39,
      "name": "Solid Black Chunky Boots",
      "brand": "DressBerry",
      "price_inr": 1464.0,
      "rating": 5.0,
      "gender": "women",
      "wear_type": "footwear",
      "category": "boots",
      "category_label": "boots",
      "occasion": "winter",
      "image_path": "D:\\DarexAi\\images\\myntra\\41756001.jpg",
      "embed_text": "Solid Black Chunky Boots | DressBerry | boots | winter | footwear | women footwear boots winter DressBerry | A pair of Black winter boots, has high-top ankle and zip fastening and back detail | synthe",
      "has_image": true
    },
    "myntra_38487469": {
      "index": 40,
      "name": "Party Block Pumps with Buckles",
      "brand": "CHINRAAG",
      "price_inr": 768.0,
      "rating": 4.1,
      "gender": "women",
      "wear_type": "footwear",
      "category": "ethnic-footwear",
      "category_label": "ethnic footwear",
      "occasion": "festive",
      "image_path": "D:\\DarexAi\\images\\myntra\\38487469.jpg",
      "embed_text": "Party Block Pumps with Buckles | CHINRAAG | ethnic footwear | festive | footwear | women footwear ethnic-footwear festive CHINRAAG | A pair of maroon and maroon pumps ,has regular ankle and backstrap ",
      "has_image": true
    },
    "ajio_701467182": {
      "index": 41,
      "name": "Women Floral Print Maxi Fit & Flare Dress",
      "brand": "LEIA",
      "price_inr": 775.0,
      "rating": 1.0,
      "gender": "women",
      "wear_type": "western",
      "category": "maxi-dresses",
      "category_label": "maxi dresses",
      "occasion": "vacation",
      "image_path": "D:\\DarexAi\\images\\ajio\\701467182.jpg",
      "embed_text": "Women Floral Print Maxi Fit & Flare Dress | LEIA | maxi dresses | vacation | western | women western maxi-dresses vacation LEIA | Navy maxi dress for women from LEIA. It features a floral print. A ver",
      "has_image": true
    },
    "ajio_703543037": {
      "index": 42,
      "name": "Women 2-Piece Co-Ord Set",
      "brand": "Lulu & Sky",
      "price_inr": 3104.0,
      "rating": 0.0,
      "gender": "women",
      "wear_type": "western",
      "category": "co-ord-sets",
      "category_label": "co ord sets",
      "occasion": "party",
      "image_path": "D:\\DarexAi\\images\\ajio\\703543037.jpg",
      "embed_text": "Women 2-Piece Co-Ord Set | Lulu & Sky | co ord sets | party | western | women western co-ord-sets party Lulu & Sky | Brown co ord set for women from Lulu & Sky. A standout choice for parties and eveni",
      "has_image": true
    },
    "ajio_702390240": {
      "index": 43,
      "name": "Women Slip-On Flat Sandals",
      "brand": "JM LOOKS",
      "price_inr": 538.0,
      "rating": 3.4,
      "gender": "women",
      "wear_type": "footwear",
      "category": "flats",
      "category_label": "flats",
      "occasion": "casual",
      "image_path": "D:\\DarexAi\\images\\ajio\\702390240.jpg",
      "embed_text": "Women Slip-On Flat Sandals | JM LOOKS | flats | casual | footwear | women footwear flats casual JM LOOKS | Brown pair of flats for women from JM LOOKS. Easy to dress down for everyday casual wear.",
      "has_image": true
    },
    "ajio_701677398": {
      "index": 44,
      "name": "Women Embellished Clutch with Lock",
      "brand": "Rubans",
      "price_inr": 563.0,
      "rating": 0.0,
      "gender": "women",
      "wear_type": "accessory",
      "category": "clutches",
      "category_label": "clutches",
      "occasion": "party",
      "image_path": "D:\\DarexAi\\images\\ajio\\701677398.jpg",
      "embed_text": "Women Embellished Clutch with Lock | Rubans | clutches | party | accessory | women accessory clutches party Rubans | White clutch for women from Rubans. It features embellishments. A standout choice f",
      "has_image": true
    },
    "nykaa_13632320": {
      "index": 45,
      "name": "Ultimate Cotton Flare Leggings with Anti-Slip Waist & Pockets NYAT503 Jet Black",
      "brand": "Nykd by Nykaa",
      "price_inr": 1229.0,
      "rating": 4.1,
      "gender": "women",
      "wear_type": "western",
      "category": "leggings",
      "category_label": "leggings",
      "occasion": "sports",
      "image_path": "D:\\DarexAi\\images\\nykaa\\13632320.jpg",
      "embed_text": "Ultimate Cotton Flare Leggings with Anti-Slip Waist & Pockets NYAT503 Jet Black | Nykd by Nykaa | leggings | sports | western | women western leggings sports Nykd by Nykaa | Buy Ultimate Cotton Flare ",
      "has_image": true
    },
    "ajio_702733799": {
      "index": 46,
      "name": "Women Embroidered Straight Kurta Suit Set",
      "brand": "SVARAA",
      "price_inr": 942.0,
      "rating": 0.0,
      "gender": "women",
      "wear_type": "ethnic",
      "category": "kurta-sets",
      "category_label": "kurta sets",
      "occasion": "festive",
      "image_path": "D:\\DarexAi\\images\\ajio\\702733799.jpg",
      "embed_text": "Women Embroidered Straight Kurta Suit Set | SVARAA | kurta sets | festive | ethnic | women ethnic kurta-sets festive SVARAA | Navy kurta set for women from SVARAA. It features embroidery. Suited to fe",
      "has_image": true
    },
    "ajio_702454568": {
      "index": 47,
      "name": "Women Embellished Anarkali Kurta Suit Set",
      "brand": "SVARAA",
      "price_inr": 1599.0,
      "rating": 1.0,
      "gender": "women",
      "wear_type": "ethnic",
      "category": "salwar-suits",
      "category_label": "salwar suits",
      "occasion": "festive",
      "image_path": "D:\\DarexAi\\images\\ajio\\702454568.jpg",
      "embed_text": "Women Embellished Anarkali Kurta Suit Set | SVARAA | salwar suits | festive | ethnic | women ethnic salwar-suits festive SVARAA | Grey salwar suit for women from SVARAA. It features embellishments. Su",
      "has_image": true
    },
    "ajio_702780607": {
      "index": 48,
      "name": "Button Closure Long Coat",
      "brand": "Cantabil",
      "price_inr": 4000.0,
      "rating": 0.0,
      "gender": "women",
      "wear_type": "western",
      "category": "long-coats",
      "category_label": "long coats",
      "occasion": "winter",
      "image_path": "D:\\DarexAi\\images\\ajio\\702780607.jpg",
      "embed_text": "Button Closure Long Coat | Cantabil | long coats | winter | western | women western long-coats winter Cantabil | Grey long coat for women from Cantabil. A versatile addition to the wardrobe.",
      "has_image": true
    },
    "myntra_36090580": {
      "index": 49,
      "name": "Shopper Shoulder Bag",
      "brand": "MANGO",
      "price_inr": 1595.0,
      "rating": 4.5,
      "gender": "women",
      "wear_type": "accessory",
      "category": "handbags",
      "category_label": "handbags",
      "occasion": "office",
      "image_path": "D:\\DarexAi\\images\\myntra\\36090580.jpg",
      "embed_text": "Shopper Shoulder Bag | MANGO | handbags | office | accessory | women accessory handbags office MANGO | Olive solid shoulder bag, 1 main compartment, has a zip closure, 1 external pocket, 1 inner pocke",
      "has_image": true
    },
    "myntra_24130018": {
      "index": 50,
      "name": "Sling Bag with Quilted",
      "brand": "Exotic",
      "price_inr": 849.0,
      "rating": 4.6,
      "gender": "women",
      "wear_type": "accessory",
      "category": "handbags",
      "category_label": "handbags",
      "occasion": "office",
      "image_path": "D:\\DarexAi\\images\\myntra\\24130018.jpg",
      "embed_text": "Sling Bag with Quilted | Exotic | handbags | office | accessory | women accessory handbags office Exotic | Black solid shoulder bag, with quilted detail | 2 main compartments, has a zip closure, 2 inn",
      "has_image": true
    },
    "myntra_15660676": {
      "index": 51,
      "name": "Sparkle Framed Clutch",
      "brand": "Lavie",
      "price_inr": 649.0,
      "rating": 4.5,
      "gender": "women",
      "wear_type": "accessory",
      "category": "clutches",
      "category_label": "clutches",
      "occasion": "party",
      "image_path": "D:\\DarexAi\\images\\myntra\\15660676.jpg",
      "embed_text": "Sparkle Framed Clutch | Lavie | clutches | party | accessory | women accessory clutches party Lavie | Rose solid box clutches | Has shoulder strap | 1 main compartment with button closure",
      "has_image": true
    },
    "myntra_39451752": {
      "index": 52,
      "name": "Women PU Clutches",
      "brand": "ESBEDA",
      "price_inr": 790.0,
      "rating": 4.8,
      "gender": "women",
      "wear_type": "accessory",
      "category": "clutches",
      "category_label": "clutches",
      "occasion": "party",
      "image_path": "D:\\DarexAi\\images\\myntra\\39451752.jpg",
      "embed_text": "Women PU Clutches | ESBEDA | clutches | party | accessory | women accessory clutches party ESBEDA | Black and Gold-Toned printed Purse clutches | Has Shoulder Strap | 1 main compartment with Click clo",
      "has_image": true
    },
    "myntra_41578752": {
      "index": 53,
      "name": "Embroidered Potli Clutch",
      "brand": "Anouk",
      "price_inr": 974.0,
      "rating": 0.0,
      "gender": "women",
      "wear_type": "accessory",
      "category": "clutches",
      "category_label": "clutches",
      "occasion": "party",
      "image_path": "D:\\DarexAi\\images\\myntra\\41578752.jpg",
      "embed_text": "Embroidered Potli Clutch | Anouk | clutches | party | accessory | women accessory clutches party Anouk | Gold-toned Embroidered Potli clutches | Has Wrist Loop | 1 main compartment with Drawstring clo",
      "has_image": true
    },
    "myntra_625852": {
      "index": 54,
      "name": "Drop Earrings",
      "brand": "Zaveri Pearls",
      "price_inr": 270.0,
      "rating": 4.5,
      "gender": "women",
      "wear_type": "accessory",
      "category": "earrings",
      "category_label": "earrings",
      "occasion": "festive",
      "image_path": "D:\\DarexAi\\images\\myntra\\625852.jpg",
      "embed_text": "Drop Earrings | Zaveri Pearls | earrings | festive | accessory | women accessory earrings festive Zaveri Pearls | A pair of maroon and off-white drop earrings with gold-toned accent, has a stone-studd",
      "has_image": true
    },
    "myntra_7451803": {
      "index": 55,
      "name": "Gold-Plated Jewellery Set",
      "brand": "PANASH",
      "price_inr": 778.0,
      "rating": 4.3,
      "gender": "women",
      "wear_type": "accessory",
      "category": "necklaces",
      "category_label": "necklaces",
      "occasion": "wedding",
      "image_path": "D:\\DarexAi\\images\\myntra\\7451803.jpg",
      "embed_text": "Gold-Plated Jewellery Set | PANASH | necklaces | wedding | accessory | women accessory necklaces wedding PANASH | Gold-plated Kundan stone-studded Jewellery Set | Gold-plated and white embellished nec",
      "has_image": true
    },
    "myntra_30441198": {
      "index": 56,
      "name": "Single-Breasted Formal Blazers",
      "brand": "Van Heusen Woman",
      "price_inr": 2369.0,
      "rating": 4.8,
      "gender": "women",
      "wear_type": "western",
      "category": "blazers",
      "category_label": "blazers",
      "occasion": "office",
      "image_path": "D:\\DarexAi\\images\\myntra\\30441198.jpg",
      "embed_text": "Single-Breasted Formal Blazers | Van Heusen Woman | blazers | office | western | women western blazers office Van Heusen Woman | Navy blue checked regular-fit blazer, has a notched lapel collar, singl",
      "has_image": true
    },
    "nykaa_24377703": {
      "index": 57,
      "name": "Women Malak Brown Solid Juttis",
      "brand": "YASSIO",
      "price_inr": 1200.0,
      "rating": 0.0,
      "gender": "women",
      "wear_type": "footwear",
      "category": "ethnic-footwear",
      "category_label": "ethnic footwear",
      "occasion": "festive",
      "image_path": "D:\\DarexAi\\images\\nykaa\\24377703.jpg",
      "embed_text": "Women Malak Brown Solid Juttis | YASSIO | ethnic footwear | festive | footwear | women footwear ethnic-footwear festive YASSIO | Buy YASSIO Women Malak Brown Solid Juttis (UK 4) online at best prices ",
      "has_image": true
    },
    "nykaa_22909654": {
      "index": 58,
      "name": "Brown UV Protection Oval Full Rim Casual Women Sunglass - VS 2301-Gold-BRN (40)",
      "brand": "HASHTAG EYEWEAR",
      "price_inr": 699.0,
      "rating": 0.0,
      "gender": "women",
      "wear_type": "accessory",
      "category": "sunglasses",
      "category_label": "sunglasses",
      "occasion": "vacation",
      "image_path": "D:\\DarexAi\\images\\nykaa\\22909654.jpg",
      "embed_text": "Brown UV Protection Oval Full Rim Casual Women Sunglass - VS 2301-Gold-BRN (40) | HASHTAG EYEWEAR | sunglasses | vacation | accessory | women accessory sunglasses vacation HASHTAG EYEWEAR | Buy HASHTA",
      "has_image": true
    },
    "ajio_702013278": {
      "index": 59,
      "name": "Men Slip-On Formal Shoes",
      "brand": "REGAL",
      "price_inr": 3990.0,
      "rating": 0.0,
      "gender": "men",
      "wear_type": "footwear",
      "category": "formal-shoes",
      "category_label": "formal shoes",
      "occasion": "office",
      "image_path": "D:\\DarexAi\\images\\ajio\\702013278.jpg",
      "embed_text": "Men Slip-On Formal Shoes | REGAL | formal shoes | office | footwear | men footwear formal-shoes office REGAL | Brown pair of formal shoes for men from REGAL. Well suited to office and formal settings.",
      "has_image": true
    },
    "ajio_700917335": {
      "index": 60,
      "name": "Men Formal Lace-Up Shoes with Faux Leather Upper",
      "brand": "KOSHER",
      "price_inr": 1500.0,
      "rating": 3.7,
      "gender": "men",
      "wear_type": "footwear",
      "category": "formal-shoes",
      "category_label": "formal shoes",
      "occasion": "office",
      "image_path": "D:\\DarexAi\\images\\ajio\\700917335.jpg",
      "embed_text": "Men Formal Lace-Up Shoes with Faux Leather Upper | KOSHER | formal shoes | office | footwear | men footwear formal-shoes office KOSHER | Black pair of formal shoes for men from KOSHER. It features a l",
      "has_image": true
    },
    "ajio_469683825": {
      "index": 61,
      "name": "Men Patterned Low-Top Loafers",
      "brand": "U.S. Polo Assn.",
      "price_inr": 1610.0,
      "rating": 3.4,
      "gender": "men",
      "wear_type": "footwear",
      "category": "loafers",
      "category_label": "loafers",
      "occasion": "casual",
      "image_path": "D:\\DarexAi\\images\\ajio\\469683825.jpg",
      "embed_text": "Men Patterned Low-Top Loafers | U.S. Polo Assn. | loafers | casual | footwear | men footwear loafers casual U.S. Polo Assn. | Black pair of loafers for men from U.S. Polo Assn.. Easy to dress down for",
      "has_image": true
    },
    "ajio_700692049": {
      "index": 62,
      "name": "Men Double-Strap Slip-On Sandals",
      "brand": "SPYKAR",
      "price_inr": 1100.0,
      "rating": 3.6,
      "gender": "men",
      "wear_type": "footwear",
      "category": "sandals",
      "category_label": "sandals",
      "occasion": "vacation",
      "image_path": "D:\\DarexAi\\images\\ajio\\700692049.jpg",
      "embed_text": "Men Double-Strap Slip-On Sandals | SPYKAR | sandals | vacation | footwear | men footwear sandals vacation SPYKAR | Olive pair of sandals for men from SPYKAR. A versatile addition to the wardrobe.",
      "has_image": true
    },
    "ajio_701984081": {
      "index": 63,
      "name": "Men Ankle-Length Chelsea Boots with Lace Fastening",
      "brand": "BUCIK",
      "price_inr": 595.0,
      "rating": 3.5,
      "gender": "men",
      "wear_type": "footwear",
      "category": "boots",
      "category_label": "boots",
      "occasion": "winter",
      "image_path": "D:\\DarexAi\\images\\ajio\\701984081.jpg",
      "embed_text": "Men Ankle-Length Chelsea Boots with Lace Fastening | BUCIK | boots | winter | footwear | men footwear boots winter BUCIK | Brown pair of boots for men from BUCIK. A versatile addition to the wardrobe.",
      "has_image": true
    },
    "ajio_464207650": {
      "index": 64,
      "name": "Men Elevator Casual Heeled Slip-on Traditional Jutti",
      "brand": "BXXY",
      "price_inr": 1400.0,
      "rating": 2.0,
      "gender": "men",
      "wear_type": "footwear",
      "category": "ethnic-footwear",
      "category_label": "ethnic footwear",
      "occasion": "wedding",
      "image_path": "D:\\DarexAi\\images\\ajio\\464207650.jpg",
      "embed_text": "Men Elevator Casual Heeled Slip-on Traditional Jutti | BXXY | ethnic footwear | wedding | footwear | men footwear ethnic-footwear wedding BXXY | Brown pair of ethnic footwear for men from BXXY. Made f",
      "has_image": true
    },
    "ajio_4935353720": {
      "index": 65,
      "name": "Men Analogue Watch-NU1825SL16",
      "brand": "TITAN",
      "price_inr": 2236.0,
      "rating": 0.0,
      "gender": "men",
      "wear_type": "accessory",
      "category": "watches",
      "category_label": "watches",
      "occasion": "office",
      "image_path": "D:\\DarexAi\\images\\ajio\\4935353720.jpg",
      "embed_text": "Men Analogue Watch-NU1825SL16 | TITAN | watches | office | accessory | men accessory watches office TITAN | Multicoloured watch for men from TITAN. Well suited to office and formal settings.",
      "has_image": true
    },
    "ajio_4934125790": {
      "index": 66,
      "name": "Men Water-Resistant Analogue Watch-90200SL04",
      "brand": "TITAN",
      "price_inr": 7697.0,
      "rating": 0.0,
      "gender": "men",
      "wear_type": "accessory",
      "category": "watches",
      "category_label": "watches",
      "occasion": "office",
      "image_path": "D:\\DarexAi\\images\\ajio\\4934125790.jpg",
      "embed_text": "Men Water-Resistant Analogue Watch-90200SL04 | TITAN | watches | office | accessory | men accessory watches office TITAN | Multicoloured watch for men from TITAN. Well suited to office and formal sett",
      "has_image": true
    },
    "ajio_702546309": {
      "index": 67,
      "name": "ANIME - Men Baseball Caps",
      "brand": "BEWAKOOF",
      "price_inr": 383.0,
      "rating": 4.0,
      "gender": "men",
      "wear_type": "accessory",
      "category": "caps",
      "category_label": "caps",
      "occasion": "sports",
      "image_path": "D:\\DarexAi\\images\\ajio\\702546309.jpg",
      "embed_text": "ANIME - Men Baseball Caps | BEWAKOOF | caps | sports | accessory | men accessory caps sports BEWAKOOF | Olive cap for men from BEWAKOOF. Built for workouts and active days.",
      "has_image": true
    }
  }
}